RandomGetter-0.0.8.data/scripts/random_getter.py
RandomGetter-0.0.8.dist-info/DESCRIPTION.rst
RandomGetter-0.0.8.dist-info/metadata.json
RandomGetter-0.0.8.dist-info/WHEEL
RandomGetter-0.0.8.dist-info/METADATA
RandomGetter-0.0.8.dist-info/RECORD
RandomGetter-0.0.8.dist-info/top_level.txt
random_getter/random_getter.py
random_getter/__init__.py
