Metadata-Version: 2.0
Name: RandomGetter
Version: 0.0.8
Summary: This project provides a tools for getting various format or kind Random Value.
Home-page: https://github.com/yassu/RandomGetter
Author: yassu
Author-email: mathyassu@gmail.com
License: Released Under the Apache license
